okareo_tests/__init__.py
okareo_tests/check_error_raise.py
okareo_tests/check_tool_call.py
okareo_tests/checks/input_comparison_check.py
okareo_tests/checks/metadata_check.py
okareo_tests/checks/model_input_check.py
okareo_tests/checks/model_output_check.py
okareo_tests/checks/sample_check.py
okareo_tests/checks/sample_check_with_explanation.py
okareo_tests/checks/scenario_input_check.py
okareo_tests/checks/scenario_result_check.py
okareo_tests/common.py
okareo_tests/conftest.py
okareo_tests/datasets/README.md
okareo_tests/datasets/random_sentence_tiny.txt
okareo_tests/json_scenario.jsonl
okareo_tests/prompts/frustrated_driver.txt
okareo_tests/test_autogen_logger.py
okareo_tests/test_checks.py
okareo_tests/test_client.py
okareo_tests/test_crewai_logger.py
okareo_tests/test_dialog_scenario.py
okareo_tests/test_generation_model.py
okareo_tests/test_get_data_points.py
okareo_tests/test_integration_checks.py
okareo_tests/test_integration_model_under_test.py
okareo_tests/test_integration_multiturn.py
okareo_tests/test_json_scenario.py
okareo_tests/test_langchain.py
okareo_tests/test_litellm_logger.py
okareo_tests/test_model_invocation.py
okareo_tests/test_model_under_test.py
okareo_tests/test_model_under_test_async.py
okareo_tests/test_projects.py
okareo_tests/test_register_model.py
okareo_tests/test_reporter.py
okareo_tests/test_retrieval.py
okareo_tests/test_run_errors.py
okareo_tests/test_run_scenario_errors.py
okareo_tests/test_scenario_template.py
okareo_tests/test_scenarios.py
okareo_tests/test_traces.py
okareo_tests/test_voice_multiturn.py
okareo_tests/test_voice_simulation.py
okareo_tests/utils.py
okareo_tests/webbizz_1_test_article.jsonl
okareo_tests/webbizz_3_test_article.jsonl
okareo_tests/webbizz_3_test_article_classification.jsonl
okareo_tests/webbizz_51_test_articles.jsonl
okareo_tests/webbizz_class_conditional.jsonl
okareo_tests/webbizz_class_rephrase.jsonl
okareo_tests/webbizz_class_seed.jsonl
okareo_tests/webbizz_retrieval_questions.jsonl
okareo-0.0.118.dist-info/METADATA
okareo-0.0.118.dist-info/WHEEL
okareo-0.0.118.dist-info/licenses/LICENSE
okareo-0.0.118.dist-info/RECORD
