Metadata-Version: 2.4
Name: okareo
Version: 0.0.118
Summary: Python SDK for interacting with Okareo Cloud APIs
License: Apache-2.0
License-File: LICENSE
Author: Okareo
Author-email: info@okareo.com
Requires-Python: >=3.10,<3.13
Classifier: Development Status :: 4 - Beta
Classifier: Intended Audience :: Developers
Classifier: License :: OSI Approved :: Apache Software License
Classifier: Operating System :: OS Independent
Classifier: Programming Language :: Python
Classifier: Programming Language :: Python :: 3
Classifier: Programming Language :: Python :: 3.10
Classifier: Programming Language :: Python :: 3.11
Classifier: Programming Language :: Python :: 3.12
Classifier: Topic :: Software Development :: Libraries :: Python Modules
Classifier: Typing :: Typed
Provides-Extra: autogen
Provides-Extra: langchain
Provides-Extra: voice
Requires-Dist: aiohttp (>=3.10.0,<4.0.0)
Requires-Dist: attrs (>=23.1.0,<24.0.0)
Requires-Dist: autogen-agentchat (>=0.2.36,<0.3.0) ; extra == "autogen"
Requires-Dist: httpx (>=0.23)
Requires-Dist: langchain (>=0.0.321,<0.0.322) ; extra == "langchain"
Requires-Dist: litellm (>=1.29.5,<2.0.0) ; extra == "langchain"
Requires-Dist: nats-py (>=2.4.0,<3.0.0)
Requires-Dist: nkeys (>=0.2.0,<0.3.0)
Requires-Dist: numpy (>=1.21.0,<2.0) ; extra == "voice"
Requires-Dist: openai (>=1.20.0,<2.0.0) ; extra == "langchain"
Requires-Dist: opentelemetry-api (>=1.0.0)
Requires-Dist: opentelemetry-instrumentation (>=0.40b.0)
Requires-Dist: opentelemetry-proto (>=1.20.0)
Requires-Dist: opentelemetry-sdk (>=1.0.0)
Requires-Dist: protobuf (>=2.6.1)
Requires-Dist: pydantic (>=1.0.0)
Requires-Dist: pydoc-markdown (>=4.8.2,<5.0.0)
Requires-Dist: pynacl (>=1.5.0,<2.0.0)
Requires-Dist: python-dateutil (>=2.8.2,<3.0.0)
Requires-Dist: scipy (>=1.10.0,<2.0.0) ; extra == "voice"
Requires-Dist: tqdm (>=4.67.1,<5.0.0)
Requires-Dist: types-python-dateutil (>=2.8.19.14,<3.0.0.0)
Requires-Dist: websockets (>=15.0.1,<16.0.0) ; extra == "voice"
Project-URL: Documentation, https://docs.okareo.com/docs/getting-started/overview
Project-URL: Homepage, https://okareo.com
Project-URL: Repository, https://github.com/okareo-ai/okareo-python-sdk
